{
    "coreCurrencyItems": [
        {
            "id": "divine",
            "name": "Divine Orb",
            "image": "/gen/image/WzI1LDE0LHsiZiI6IjJESXRlbXMvQ3VycmVuY3kvQ3VycmVuY3lNb2RWYWx1ZXMiLCJzY2FsZSI6MSwicmVhbG0iOiJwb2UyIn1d/2986e220b3/CurrencyModValues.png",
            "category": "Currency"
        },
        {
            "id": "exalted",
            "name": "Exalted Orb",
            "image": "/gen/image/WzI1LDE0LHsiZiI6IjJESXRlbXMvQ3VycmVuY3kvQ3VycmVuY3lBZGRNb2RUb1JhcmUiLCJzY2FsZSI6MSwicmVhbG0iOiJwb2UyIn1d/ad7c366789/CurrencyAddModToRare.png",
            "category": "Currency"
        },
        {
            "id": "chaos",
            "name": "Chaos Orb",
            "image": "/gen/image/WzI1LDE0LHsiZiI6IjJESXRlbXMvQ3VycmVuY3kvQ3VycmVuY3lSZXJvbGxSYXJlIiwic2NhbGUiOjEsInJlYWxtIjoicG9lMiJ9XQ/c0ca392a78/CurrencyRerollRare.png",
            "category": "Currency"
        }
    ],
    "items": [
        {
            "item": {
                "id": "ancient-crisis-fragment",
                "name": "Ancient Crisis Fragment",
                "image": "/gen/image/WzI1LDE0LHsiZiI6IjJESXRlbXMvUXVlc3RJdGVtcy9QaW5uYWNsZUtleTEiLCJzY2FsZSI6MSwicmVhbG0iOiJwb2UyIn1d/ef329c74d1/PinnacleKey1.png",
                "category": "Fragments"
            },
            "rate": {
                "divine": 20.70909090909091,
                "exalted": 0.03012034357631712,
                "chaos": 0.5298245614035088
            },
            "sparklines": {},
            "volumes": {
                "divine": 379.6666666666667,
                "exalted": 437.1666666666667,
                "chaos": 100.66666666666667
            },
            "primaryValue": 0.03685033031836607,
            "volumePrimaryValue": 16.109736070845702,
            "maxVolumeCurrency": "exalted"
        },
        {
            "item": {
                "id": "cowardly-fate",
                "name": "Cowardly Fate",
                "image": "/gen/image/WzI1LDE0LHsiZiI6IjJESXRlbXMvQ3VycmVuY3kvU291bENvcmVzL1RyaWFsbWFzdGVyS2V5MSIsInNjYWxlIjoxLCJyZWFsbSI6InBvZTIifV0/661ab60074/TrialmasterKey1.png",
                "category": "Fragments"
            },
            "rate": {
                "divine": 6.75,
                "exalted": 0.011804412522652834,
                "chaos": 0.25884016973125884
            },
            "sparklines": {},
            "volumes": {
                "divine": 9,
                "exalted": 118.33333333333333,
                "chaos": 30.5
            },
            "primaryValue": 0.09402794149729707,
            "volumePrimaryValue": 11.12663974384682,
            "maxVolumeCurrency": "exalted"
        },
        {
            "item": {
                "id": "deadly-fate",
                "name": "Deadly Fate",
                "image": "/gen/image/WzI1LDE0LHsiZiI6IjJESXRlbXMvQ3VycmVuY3kvU291bENvcmVzL1RyaWFsbWFzdGVyS2V5MiIsInNjYWxlIjoxLCJyZWFsbSI6InBvZTIifV0/cccae44832/TrialmasterKey2.png",
                "category": "Fragments"
            },
            "rate": {
                "divine": 5.7,
                "exalted": 0.0116458468123227,
                "chaos": 0.22297297297297297
            },
            "sparklines": {},
            "volumes": {
                "divine": 9.5,
                "exalted": 117,
                "chaos": 27.5
            },
            "primaryValue": 0.09530819252366494,
            "volumePrimaryValue": 11.151058525268798,
            "maxVolumeCurrency": "exalted"
        },
        {
            "item": {
                "id": "primary-calamity-fragment",
                "name": "Primary Calamity Fragment",
                "image": "/gen/image/WzI1LDE0LHsiZiI6IjJESXRlbXMvUXVlc3RJdGVtcy9VYmVyUGlubmFjbGVLZXkxIiwic2NhbGUiOjEsInJlYWxtIjoicG9lMiJ9XQ/fc0875d40b/UberPinnacleKey1.png",
                "category": "Fragments"
            },
            "rate": {
                "divine": 0.509033154655549,
                "exalted": 0.0007931467866262432,
                "chaos": 0.014708573740331545
            },
            "sparklines": {},
            "volumes": {
                "divine": 854.6666666666666,
                "exalted": 99.5,
                "chaos": 254.5
            },
            "primaryValue": 1.9645085803432136,
            "volumePrimaryValue": 1679.0,
            "maxVolumeCurrency": "divine"
        },
        {
            "item": {
                "id": "runic-splinter",
                "name": "Runic Splinter",
                "image": "/gen/image/WzI1LDE0LHsiZiI6IjJESXRlbXMvQ3VycmVuY3kvRXhwZWRpdGlvbi9FeHBlZGl0aW9uU3BsaW50ZXIiLCJzY2FsZSI6MSwicmVhbG0iOiJwb2UyIn1d/4768efb2c6/ExpeditionSplinter.png",
                "category": "Fragments"
            },
            "rate": {
                "divine": 87.3171692169217,
                "exalted": 0.11961350569691502,
                "chaos": 2.49706238119924
            },
            "sparklines": {},
            "volumes": {
                "divine": 129345.83333333333,
                "exalted": 18824.833333333332,
                "chaos": 4816.833333333333
            },
            "primaryValue": 0.011452501369068712,
            "volumePrimaryValue": 1481.3333333333333,
            "maxVolumeCurrency": "divine"
        },
        {
            "item": {
                "id": "secondary-calamity-fragment",
                "name": "Secondary Calamity Fragment",
                "image": "/gen/image/WzI1LDE0LHsiZiI6IjJESXRlbXMvUXVlc3RJdGVtcy9VYmVyUGlubmFjbGVLZXkyIiwic2NhbGUiOjEsInJlYWxtIjoicG9lMiJ9XQ/0fec2b1925/UberPinnacleKey2.png",
                "category": "Fragments"
            },
            "rate": {
                "divine": 0.5287158528715853,
                "exalted": 0.0008311812035167024,
                "chaos": 0.015198640169255529
            },
            "sparklines": {},
            "volumes": {
                "divine": 819.3333333333334,
                "exalted": 115.16666666666667,
                "chaos": 280.1666666666667
            },
            "primaryValue": 1.8913751017087064,
            "volumePrimaryValue": 1549.6666666666667,
            "maxVolumeCurrency": "divine"
        },
        {
            "item": {
                "id": "tertiary-calamity-fragment",
                "name": "Tertiary Calamity Fragment",
                "image": "/gen/image/WzI1LDE0LHsiZiI6IjJESXRlbXMvUXVlc3RJdGVtcy9VYmVyUGlubmFjbGVLZXkzIiwic2NhbGUiOjEsInJlYWxtIjoicG9lMiJ9XQ/29665daa60/UberPinnacleKey3.png",
                "category": "Fragments"
            },
            "rate": {
                "divine": 0.6242641117395822,
                "exalted": 0.0010021985100744676,
                "chaos": 0.018394137435014554
            },
            "sparklines": {},
            "volumes": {
                "divine": 901.3333333333334,
                "exalted": 116.16666666666667,
                "chaos": 270.6666666666667
            },
            "primaryValue": 1.6018860946745561,
            "volumePrimaryValue": 1443.8333333333333,
            "maxVolumeCurrency": "divine"
        },
        {
            "item": {
                "id": "twilight-reliquary-key",
                "name": "Twilight Reliquary Key",
                "image": "/gen/image/WzI1LDE0LHsiZiI6IjJESXRlbXMvTWFwcy9Ud2lsaWdodE9yZGVyUmVsaXF1YXJ5S2V5V29ybGQiLCJzY2FsZSI6MSwicmVhbG0iOiJwb2UyIn1d/27f2d492e7/TwilightOrderReliquaryKeyWorld.png",
                "category": "Fragments"
            },
            "rate": {
                "divine": 97.61538461538461,
                "exalted": 0.4618913719106112,
                "chaos": 7.097560975609756
            },
            "sparklines": {},
            "volumes": {
                "divine": 634.5,
                "exalted": 2600.8333333333335,
                "chaos": 97
            },
            "primaryValue": 0.0024030425281569593,
            "volumePrimaryValue": 6.249913108648225,
            "maxVolumeCurrency": "exalted"
        },
        {
            "item": {
                "id": "weathered-crisis-fragment",
                "name": "Weathered Crisis Fragment",
                "image": "/gen/image/WzI1LDE0LHsiZiI6IjJESXRlbXMvUXVlc3RJdGVtcy9QaW5uYWNsZUtleTMiLCJzY2FsZSI6MSwicmVhbG0iOiJwb2UyIn1d/32e6544250/PinnacleKey3.png",
                "category": "Fragments"
            },
            "rate": {
                "divine": 11.846666666666666,
                "exalted": 0.016268574423622787,
                "chaos": 0.3897719419488597
            },
            "sparklines": {},
            "volumes": {
                "divine": 296.1666666666667,
                "exalted": 398.3333333333333,
                "chaos": 94
            },
            "primaryValue": 0.06822629821075571,
            "volumePrimaryValue": 27.176808787284358,
            "maxVolumeCurrency": "exalted"
        },
        {
            "item": {
                "id": "against-the-darkness",
                "name": "Zarokh's Reliquary Key: Against the Darkness",
                "image": "/gen/image/WzI1LDE0LHsiZiI6IjJESXRlbXMvTWFwcy9Ud2lsaWdodE9yZGVyUmVsaXF1YXJ5S2V5U2FuY3R1bTIiLCJzY2FsZSI6MSwicmVhbG0iOiJwb2UyIn1d/a9e91de8f5/TwilightOrderReliquaryKeySanctum2.png",
                "category": "Fragments"
            },
            "rate": {
                "divine": 0.04017857142857143
            },
            "sparklines": {},
            "volumes": {
                "divine": 1.5
            },
            "primaryValue": 24.88888888888889,
            "volumePrimaryValue": 37.333333333333336,
            "maxVolumeCurrency": "divine"
        },
        {
            "item": {
                "id": "olroths-reliquary-key",
                "name": "Olroth's Reliquary Key",
                "image": "/gen/image/WzI1LDE0LHsiZiI6IjJESXRlbXMvTWFwcy9Ud2lsaWdodE9yZGVyUmVsaXF1YXJ5S2V5RXhwZWRpdGlvbiIsInNjYWxlIjoxLCJyZWFsbSI6InBvZTIifV0/0433c7beb8/TwilightOrderReliquaryKeyExpedition.png",
                "category": "Fragments"
            },
            "rate": {
                "divine": 0.14583333333333334,
                "exalted": 0.0006131207847946045
            },
            "sparklines": {},
            "volumes": {
                "divine": 5.833333333333333,
                "exalted": 0.16666666666666666
            },
            "primaryValue": 6.857142857142857,
            "volumePrimaryValue": 40.0,
            "maxVolumeCurrency": "divine"
        },
        {
            "item": {
                "id": "tangmazus-reliquary-key",
                "name": "Tangmazu's Reliquary Key",
                "image": "/gen/image/WzI1LDE0LHsiZiI6IjJESXRlbXMvTWFwcy9Ud2lsaWdodE9yZGVyUmVsaXF1YXJ5S2V5RGVsaXJpdW0iLCJzY2FsZSI6MSwicmVhbG0iOiJwb2UyIn1d/1a87e735c6/TwilightOrderReliquaryKeyDelirium.png",
                "category": "Fragments"
            },
            "rate": {
                "divine": 0.25,
                "exalted": 0.0006440705257225667
            },
            "sparklines": {},
            "volumes": {
                "divine": 13.666666666666666,
                "exalted": 1.3333333333333333
            },
            "primaryValue": 4,
            "volumePrimaryValue": 54.666666666666664,
            "maxVolumeCurrency": "divine"
        },
        {
            "item": {
                "id": "faded-crisis-fragment",
                "name": "Faded Crisis Fragment",
                "image": "/gen/image/WzI1LDE0LHsiZiI6IjJESXRlbXMvUXVlc3RJdGVtcy9QaW5uYWNsZUtleTIiLCJzY2FsZSI6MSwicmVhbG0iOiJwb2UyIn1d/5709c39ee7/PinnacleKey2.png",
                "category": "Fragments"
            },
            "rate": {
                "divine": 3.1735395189003435,
                "exalted": 0.0043068180796446654,
                "chaos": 0.07465538419544152
            },
            "sparklines": {},
            "volumes": {
                "divine": 307.8333333333333,
                "exalted": 319.3333333333333,
                "chaos": 91.16666666666667
            },
            "primaryValue": 0.25771801584466686,
            "volumePrimaryValue": 82.29795305973029,
            "maxVolumeCurrency": "exalted"
        },
        {
            "item": {
                "id": "rite-of-passage",
                "name": "Azmeri Reliquary Key",
                "image": "/gen/image/WzI1LDE0LHsiZiI6IjJESXRlbXMvTWFwcy9Ud2lsaWdodE9yZGVyUmVsaXF1YXJ5S2V5QXptZXJpIiwic2NhbGUiOjEsInJlYWxtIjoicG9lMiJ9XQ/cf47ea370f/TwilightOrderReliquaryKeyAzmeri.png",
                "category": "Fragments"
            },
            "rate": {
                "divine": 0.006030150753768844
            },
            "sparklines": {},
            "volumes": {
                "divine": 1
            },
            "primaryValue": 165.83333333333334,
            "volumePrimaryValue": 165.83333333333334,
            "maxVolumeCurrency": "divine"
        },
        {
            "item": {
                "id": "ritualistic-reliquary-key",
                "name": "Ritualistic Reliquary Key",
                "image": "/gen/image/WzI1LDE0LHsiZiI6IjJESXRlbXMvTWFwcy9Ud2lsaWdodE9yZGVyUmVsaXF1YXJ5S2V5Uml0dWFsIiwic2NhbGUiOjEsInJlYWxtIjoicG9lMiJ9XQ/d4d4229ab8/TwilightOrderReliquaryKeyRitual.png",
                "category": "Fragments"
            },
            "rate": {
                "divine": 18,
                "exalted": 0.044399223013597264,
                "chaos": 0.2222222222222222
            },
            "sparklines": {},
            "volumes": {
                "divine": 24,
                "exalted": 80,
                "chaos": 2
            },
            "primaryValue": 0.02499918995767203,
            "volumePrimaryValue": 1.9999351966137624,
            "maxVolumeCurrency": "exalted"
        },
        {
            "item": {
                "id": "the-arbiters-reliquary-key",
                "name": "The Arbiter's Reliquary Key",
                "image": "/gen/image/WzI1LDE0LHsiZiI6IjJESXRlbXMvTWFwcy9Ud2lsaWdodE9yZGVyUmVsaXF1YXJ5S2V5UGlubmFjbGUiLCJzY2FsZSI6MSwicmVhbG0iOiJwb2UyIn1d/c2e7758a33/TwilightOrderReliquaryKeyPinnacle.png",
                "category": "Fragments"
            },
            "rate": {
                "divine": 0.08849557522123894,
                "exalted": 0.0007380073800738007,
                "chaos": 0.00819672131147541
            },
            "sparklines": {},
            "volumes": {
                "divine": 8.333333333333334,
                "exalted": 0.16666666666666666,
                "chaos": 0.16666666666666666
            },
            "primaryValue": 11.3,
            "volumePrimaryValue": 94.16666666666667,
            "maxVolumeCurrency": "divine"
        },
        {
            "item": {
                "id": "the-trialmasters-reliquary-key",
                "name": "The Trialmaster's Reliquary Key",
                "image": "/gen/image/WzI1LDE0LHsiZiI6IjJESXRlbXMvTWFwcy9Ud2lsaWdodE9yZGVyUmVsaXF1YXJ5S2V5VWx0aW1hdHVtIiwic2NhbGUiOjEsInJlYWxtIjoicG9lMiJ9XQ/92ccd5ad96/TwilightOrderReliquaryKeyUltimatum.png",
                "category": "Fragments"
            },
            "rate": {
                "divine": 0.021739130434782608
            },
            "sparklines": {},
            "volumes": {
                "divine": 0.3333333333333333
            },
            "primaryValue": 46,
            "volumePrimaryValue": 15.333333333333334,
            "maxVolumeCurrency": "divine"
        },
        {
            "item": {
                "id": "victorious-fate",
                "name": "Victorious Fate",
                "image": "/gen/image/WzI1LDE0LHsiZiI6IjJESXRlbXMvQ3VycmVuY3kvU291bENvcmVzL1RyaWFsbWFzdGVyS2V5MyIsInNjYWxlIjoxLCJyZWFsbSI6InBvZTIifV0/0270951a73/TrialmasterKey3.png",
                "category": "Fragments"
            },
            "rate": {
                "divine": 7.375,
                "exalted": 0.01408647419142441,
                "chaos": 0.31499051233396586
            },
            "sparklines": {},
            "volumes": {
                "divine": 9.833333333333334,
                "exalted": 117.66666666666667,
                "chaos": 27.666666666666668
            },
            "primaryValue": 0.07879506219985663,
            "volumePrimaryValue": 9.271552318849796,
            "maxVolumeCurrency": "exalted"
        },
        {
            "item": {
                "id": "xeshts-reliquary-key",
                "name": "Xesht's Reliquary Key",
                "image": "/gen/image/WzI1LDE0LHsiZiI6IjJESXRlbXMvTWFwcy9Ud2lsaWdodE9yZGVyUmVsaXF1YXJ5S2V5QnJlYWNoIiwic2NhbGUiOjEsInJlYWxtIjoicG9lMiJ9XQ/866c9d5c45/TwilightOrderReliquaryKeyBreach.png",
                "category": "Fragments"
            },
            "rate": {
                "divine": 1.4838709677419355,
                "exalted": 0.003771289537712895,
                "chaos": 0.14285714285714285
            },
            "sparklines": {},
            "volumes": {
                "divine": 7.666666666666667,
                "exalted": 10.333333333333334,
                "chaos": 0.16666666666666666
            },
            "primaryValue": 0.29431434499804787,
            "volumePrimaryValue": 3.0412482316464944,
            "maxVolumeCurrency": "exalted"
        }
    ]
}