{
    "coreCurrencyItems": [
        {
            "id": "divine",
            "name": "Divine Orb",
            "image": "/gen/image/WzI1LDE0LHsiZiI6IjJESXRlbXMvQ3VycmVuY3kvQ3VycmVuY3lNb2RWYWx1ZXMiLCJzY2FsZSI6MSwicmVhbG0iOiJwb2UyIn1d/2986e220b3/CurrencyModValues.png",
            "category": "Currency"
        },
        {
            "id": "exalted",
            "name": "Exalted Orb",
            "image": "/gen/image/WzI1LDE0LHsiZiI6IjJESXRlbXMvQ3VycmVuY3kvQ3VycmVuY3lBZGRNb2RUb1JhcmUiLCJzY2FsZSI6MSwicmVhbG0iOiJwb2UyIn1d/ad7c366789/CurrencyAddModToRare.png",
            "category": "Currency"
        },
        {
            "id": "chaos",
            "name": "Chaos Orb",
            "image": "/gen/image/WzI1LDE0LHsiZiI6IjJESXRlbXMvQ3VycmVuY3kvQ3VycmVuY3lSZXJvbGxSYXJlIiwic2NhbGUiOjEsInJlYWxtIjoicG9lMiJ9XQ/c0ca392a78/CurrencyRerollRare.png",
            "category": "Currency"
        }
    ],
    "items": [
        {
            "item": {
                "id": "cat-talisman",
                "name": "Cat Talisman",
                "image": "/gen/image/WzI1LDE0LHsiZiI6IjJESXRlbXMvQ3VycmVuY3kvVG9ybWVudGVkU3Bpcml0U29ja2V0YWJsZXMvQXptZXJpU29ja2V0YWJsZUNhdCIsInNjYWxlIjoxLCJyZWFsbSI6InBvZTIifV0/3d5bc70405/AzmeriSocketableCat.png",
                "category": "Talismans"
            },
            "rate": {
                "exalted": 0.18597168597168598,
                "chaos": 0.21739130434782608
            },
            "sparklines": {},
            "volumes": {
                "exalted": 48.166666666666664,
                "chaos": 0.8333333333333334
            },
            "primaryValue": 0.00611168009806225,
            "volumePrimaryValue": 0.29437925805666504,
            "maxVolumeCurrency": "exalted"
        },
        {
            "item": {
                "id": "bear-talisman",
                "name": "Bear Talisman",
                "image": "/gen/image/WzI1LDE0LHsiZiI6IjJESXRlbXMvQ3VycmVuY3kvVG9ybWVudGVkU3Bpcml0U29ja2V0YWJsZXMvQXptZXJpU29ja2V0YWJsZUJlYXIiLCJzY2FsZSI6MSwicmVhbG0iOiJwb2UyIn1d/2d494d1054/AzmeriSocketableBear.png",
                "category": "Talismans"
            },
            "rate": {
                "exalted": 0.24238733252131547,
                "chaos": 1
            },
            "sparklines": {},
            "volumes": {
                "exalted": 33.166666666666664,
                "chaos": 1.6666666666666667
            },
            "primaryValue": 0.004689186683698841,
            "volumePrimaryValue": 0.15552469167601157,
            "maxVolumeCurrency": "exalted"
        },
        {
            "item": {
                "id": "owl-talisman",
                "name": "Owl Talisman",
                "image": "/gen/image/WzI1LDE0LHsiZiI6IjJESXRlbXMvQ3VycmVuY3kvVG9ybWVudGVkU3Bpcml0U29ja2V0YWJsZXMvQXptZXJpU29ja2V0YWJsZU93bCIsInNjYWxlIjoxLCJyZWFsbSI6InBvZTIifV0/dfe1212549/AzmeriSocketableOwl.png",
                "category": "Talismans"
            },
            "rate": {
                "exalted": 0.2024866785079929,
                "chaos": 0.2727272727272727
            },
            "sparklines": {},
            "volumes": {
                "exalted": 19,
                "chaos": 1
            },
            "primaryValue": 0.005613206065362813,
            "volumePrimaryValue": 0.10665091524189345,
            "maxVolumeCurrency": "exalted"
        },
        {
            "item": {
                "id": "primate-talisman",
                "name": "Primate Talisman",
                "image": "/gen/image/WzI1LDE0LHsiZiI6IjJESXRlbXMvQ3VycmVuY3kvVG9ybWVudGVkU3Bpcml0U29ja2V0YWJsZXMvQXptZXJpU29ja2V0YWJsZU1vbmtleSIsInNjYWxlIjoxLCJyZWFsbSI6InBvZTIifV0/77a4554895/AzmeriSocketableMonkey.png",
                "category": "Talismans"
            },
            "rate": {
                "exalted": 0.2774703557312253,
                "chaos": 3.1538461538461537
            },
            "sparklines": {},
            "volumes": {
                "exalted": 58.5,
                "chaos": 6.833333333333333
            },
            "primaryValue": 0.004096291472149966,
            "volumePrimaryValue": 0.23963305112077302,
            "maxVolumeCurrency": "exalted"
        },
        {
            "item": {
                "id": "talisman-of-eeshta",
                "name": "Talisman of Eeshta",
                "image": "/gen/image/WzI1LDE0LHsiZiI6IjJESXRlbXMvQ3VycmVuY3kvVG9ybWVudGVkU3Bpcml0U29ja2V0YWJsZXMvQXptZXJpU29ja2V0YWJsZU93bFNwZWNpYWwiLCJzY2FsZSI6MSwicmVhbG0iOiJwb2UyIn1d/8965465ce6/AzmeriSocketableOwlSpecial.png",
                "category": "Talismans"
            },
            "rate": {
                "divine": 6.666666666666667,
                "exalted": 0.0524073285044738,
                "chaos": 0.5
            },
            "sparklines": {},
            "volumes": {
                "divine": 3.3333333333333335,
                "exalted": 41,
                "chaos": 2.1666666666666665
            },
            "primaryValue": 0.021687796046677112,
            "volumePrimaryValue": 0.8891996379137617,
            "maxVolumeCurrency": "exalted"
        },
        {
            "item": {
                "id": "talisman-of-egrin",
                "name": "Talisman of Egrin",
                "image": "/gen/image/WzI1LDE0LHsiZiI6IjJESXRlbXMvQ3VycmVuY3kvVG9ybWVudGVkU3Bpcml0U29ja2V0YWJsZXMvQXptZXJpU29ja2V0YWJsZUNhdFNwZWNpYWwiLCJzY2FsZSI6MSwicmVhbG0iOiJwb2UyIn1d/16657ca6fc/AzmeriSocketableCatSpecial.png",
                "category": "Talismans"
            },
            "rate": {
                "exalted": 0.07476319350473613,
                "chaos": 0.5
            },
            "sparklines": {},
            "volumes": {
                "exalted": 73.66666666666667,
                "chaos": 2.6666666666666665
            },
            "primaryValue": 0.01520266054290784,
            "volumePrimaryValue": 1.1199293266608774,
            "maxVolumeCurrency": "exalted"
        },
        {
            "item": {
                "id": "talisman-of-maxarius",
                "name": "Talisman of Maxarius",
                "image": "/gen/image/WzI1LDE0LHsiZiI6IjJESXRlbXMvQ3VycmVuY3kvVG9ybWVudGVkU3Bpcml0U29ja2V0YWJsZXMvQXptZXJpU29ja2V0YWJsZVN0YWdTcGVjaWFsIiwic2NhbGUiOjEsInJlYWxtIjoicG9lMiJ9XQ/f012409342/AzmeriSocketableStagSpecial.png",
                "category": "Talismans"
            },
            "rate": {
                "exalted": 0.20930232558139536,
                "chaos": 0.25
            },
            "sparklines": {},
            "volumes": {
                "exalted": 1.5,
                "chaos": 0.16666666666666666
            },
            "primaryValue": 0.005430419603790903,
            "volumePrimaryValue": 0.008145629405686356,
            "maxVolumeCurrency": "exalted"
        },
        {
            "item": {
                "id": "talisman-of-ralakesh",
                "name": "Talisman of Ralakesh",
                "image": "/gen/image/WzI1LDE0LHsiZiI6IjJESXRlbXMvQ3VycmVuY3kvVG9ybWVudGVkU3Bpcml0U29ja2V0YWJsZXMvQXptZXJpU29ja2V0YWJsZU1vbmtleVNwZWNpYWwiLCJzY2FsZSI6MSwicmVhbG0iOiJwb2UyIn1d/8ffc9986a0/AzmeriSocketableMonkeySpecial.png",
                "category": "Talismans"
            },
            "rate": {
                "divine": 13.333333333333334,
                "exalted": 0.045112781954887216,
                "chaos": 0.7933884297520661
            },
            "sparklines": {},
            "volumes": {
                "divine": 13.333333333333334,
                "exalted": 171,
                "chaos": 32
            },
            "primaryValue": 0.02519462118502989,
            "volumePrimaryValue": 4.308280222640112,
            "maxVolumeCurrency": "exalted"
        },
        {
            "item": {
                "id": "wolf-talisman",
                "name": "Wolf Talisman",
                "image": "/gen/image/WzI1LDE0LHsiZiI6IjJESXRlbXMvQ3VycmVuY3kvVG9ybWVudGVkU3Bpcml0U29ja2V0YWJsZXMvQXptZXJpU29ja2V0YWJsZVdvbGYiLCJzY2FsZSI6MSwicmVhbG0iOiJwb2UyIn1d/c0deeb6d94/AzmeriSocketableWolf.png",
                "category": "Talismans"
            },
            "rate": {
                "exalted": 0.4177215189873418,
                "chaos": 2
            },
            "sparklines": {},
            "volumes": {
                "exalted": 11,
                "chaos": 1.3333333333333333
            },
            "primaryValue": 0.002720950203167958,
            "volumePrimaryValue": 0.029930452234847537,
            "maxVolumeCurrency": "exalted"
        },
        {
            "item": {
                "id": "boar-talisman",
                "name": "Boar Talisman",
                "image": "/gen/image/WzI1LDE0LHsiZiI6IjJESXRlbXMvQ3VycmVuY3kvVG9ybWVudGVkU3Bpcml0U29ja2V0YWJsZXMvQXptZXJpU29ja2V0YWJsZUJvYXIiLCJzY2FsZSI6MSwicmVhbG0iOiJwb2UyIn1d/5e04714fc6/AzmeriSocketableBoar.png",
                "category": "Talismans"
            },
            "rate": {
                "exalted": 1.9907407407407407
            },
            "sparklines": {},
            "volumes": {
                "exalted": 35.833333333333336
            },
            "primaryValue": 0.0005709429805175509,
            "volumePrimaryValue": 0.02045879013521224,
            "maxVolumeCurrency": "exalted"
        },
        {
            "item": {
                "id": "fox-talisman",
                "name": "Fox Talisman",
                "image": "/gen/image/WzI1LDE0LHsiZiI6IjJESXRlbXMvQ3VycmVuY3kvVG9ybWVudGVkU3Bpcml0U29ja2V0YWJsZXMvQXptZXJpU29ja2V0YWJsZUZveCIsInNjYWxlIjoxLCJyZWFsbSI6InBvZTIifV0/9d48a79d56/AzmeriSocketableFox.png",
                "category": "Talismans"
            },
            "rate": {
                "exalted": 0.05971448467966574,
                "chaos": 0.3063063063063063
            },
            "sparklines": {},
            "volumes": {
                "exalted": 57.166666666666664,
                "chaos": 5.666666666666667
            },
            "primaryValue": 0.019033898693984308,
            "volumePrimaryValue": 1.0881045420061028,
            "maxVolumeCurrency": "exalted"
        },
        {
            "item": {
                "id": "ox-talisman",
                "name": "Ox Talisman",
                "image": "/gen/image/WzI1LDE0LHsiZiI6IjJESXRlbXMvQ3VycmVuY3kvVG9ybWVudGVkU3Bpcml0U29ja2V0YWJsZXMvQXptZXJpU29ja2V0YWJsZU94Iiwic2NhbGUiOjEsInJlYWxtIjoicG9lMiJ9XQ/5ebdb092f5/AzmeriSocketableOx.png",
                "category": "Talismans"
            },
            "rate": {
                "exalted": 0.06342857142857143,
                "chaos": 1
            },
            "sparklines": {},
            "volumes": {
                "exalted": 18.5,
                "chaos": 2.3333333333333335
            },
            "primaryValue": 0.01791936072903975,
            "volumePrimaryValue": 0.3315081734872354,
            "maxVolumeCurrency": "exalted"
        },
        {
            "item": {
                "id": "rabbit-talisman",
                "name": "Rabbit Talisman",
                "image": "/gen/image/WzI1LDE0LHsiZiI6IjJESXRlbXMvQ3VycmVuY3kvVG9ybWVudGVkU3Bpcml0U29ja2V0YWJsZXMvQXptZXJpU29ja2V0YWJsZVJhYmJpdCIsInNjYWxlIjoxLCJyZWFsbSI6InBvZTIifV0/d578d6d700/AzmeriSocketableRabbit.png",
                "category": "Talismans"
            },
            "rate": {
                "divine": 36.666666666666664,
                "exalted": 0.05365373113323717,
                "chaos": 0.4868421052631579
            },
            "sparklines": {},
            "volumes": {
                "divine": 36.666666666666664,
                "exalted": 254.16666666666666,
                "chaos": 24.666666666666668
            },
            "primaryValue": 0.02118397785111612,
            "volumePrimaryValue": 5.384261037158681,
            "maxVolumeCurrency": "exalted"
        },
        {
            "item": {
                "id": "serpent-talisman",
                "name": "Serpent Talisman",
                "image": "/gen/image/WzI1LDE0LHsiZiI6IjJESXRlbXMvQ3VycmVuY3kvVG9ybWVudGVkU3Bpcml0U29ja2V0YWJsZXMvQXptZXJpU29ja2V0YWJsZVNuYWtlIiwic2NhbGUiOjEsInJlYWxtIjoicG9lMiJ9XQ/752d762312/AzmeriSocketableSnake.png",
                "category": "Talismans"
            },
            "rate": {
                "exalted": 0.5853658536585366,
                "chaos": 1
            },
            "sparklines": {},
            "volumes": {
                "exalted": 12,
                "chaos": 0.6666666666666666
            },
            "primaryValue": 0.001941690730425236,
            "volumePrimaryValue": 0.02330028876510283,
            "maxVolumeCurrency": "exalted"
        },
        {
            "item": {
                "id": "stag-talisman",
                "name": "Stag Talisman",
                "image": "/gen/image/WzI1LDE0LHsiZiI6IjJESXRlbXMvQ3VycmVuY3kvVG9ybWVudGVkU3Bpcml0U29ja2V0YWJsZXMvQXptZXJpU29ja2V0YWJsZVN0YWciLCJzY2FsZSI6MSwicmVhbG0iOiJwb2UyIn1d/2a0668f95a/AzmeriSocketableStag.png",
                "category": "Talismans"
            },
            "rate": {
                "exalted": 0.46534653465346537,
                "chaos": 0.1
            },
            "sparklines": {},
            "volumes": {
                "exalted": 15.666666666666666,
                "chaos": 0.3333333333333333
            },
            "primaryValue": 0.0024424796733527616,
            "volumePrimaryValue": 0.0382655148825266,
            "maxVolumeCurrency": "exalted"
        },
        {
            "item": {
                "id": "talisman-of-grold",
                "name": "Talisman of Grold",
                "image": "/gen/image/WzI1LDE0LHsiZiI6IjJESXRlbXMvQ3VycmVuY3kvVG9ybWVudGVkU3Bpcml0U29ja2V0YWJsZXMvQXptZXJpU29ja2V0YWJsZUJlYXJTcGVjaWFsIiwic2NhbGUiOjEsInJlYWxtIjoicG9lMiJ9XQ/363a2de335/AzmeriSocketableBearSpecial.png",
                "category": "Talismans"
            },
            "rate": {
                "divine": 10,
                "exalted": 1
            },
            "sparklines": {},
            "volumes": {
                "divine": 3.3333333333333335,
                "exalted": 0.5
            },
            "primaryValue": 0.1,
            "volumePrimaryValue": 0.3333333333333333,
            "maxVolumeCurrency": "divine"
        },
        {
            "item": {
                "id": "talisman-of-sirrius",
                "name": "Talisman of Sirrius",
                "image": "/gen/image/WzI1LDE0LHsiZiI6IjJESXRlbXMvQ3VycmVuY3kvVG9ybWVudGVkU3Bpcml0U29ja2V0YWJsZXMvQXptZXJpU29ja2V0YWJsZVdvbGZTcGVjaWFsIiwic2NhbGUiOjEsInJlYWxtIjoicG9lMiJ9XQ/53db9f9ba3/AzmeriSocketableWolfSpecial.png",
                "category": "Talismans"
            },
            "rate": {
                "divine": 0.2751362325034726,
                "exalted": 0.0003487379662458358,
                "chaos": 0.008057501258984572
            },
            "sparklines": {},
            "volumes": {
                "divine": 429.1666666666667,
                "exalted": 19,
                "chaos": 29.333333333333332
            },
            "primaryValue": 3.6345631067961164,
            "volumePrimaryValue": 1559.8333333333333,
            "maxVolumeCurrency": "divine"
        },
        {
            "item": {
                "id": "talisman-of-thruldana",
                "name": "Talisman of Thruldana",
                "image": "/gen/image/WzI1LDE0LHsiZiI6IjJESXRlbXMvQ3VycmVuY3kvVG9ybWVudGVkU3Bpcml0U29ja2V0YWJsZXMvQXptZXJpU29ja2V0YWJsZVNuYWtlU3BlY2lhbCIsInNjYWxlIjoxLCJyZWFsbSI6InBvZTIifV0/f44ebc01aa/AzmeriSocketableSnakeSpecial.png",
                "category": "Talismans"
            },
            "rate": {
                "exalted": 0.0576194086429113,
                "chaos": 1
            },
            "sparklines": {},
            "volumes": {
                "exalted": 12.666666666666666,
                "chaos": 2.1666666666666665
            },
            "primaryValue": 0.019725982593819406,
            "volumePrimaryValue": 0.24986244618837913,
            "maxVolumeCurrency": "exalted"
        }
    ]
}